azure/ai/translation/document/__init__.py
azure/ai/translation/document/_client.py
azure/ai/translation/document/_configuration.py
azure/ai/translation/document/_model_base.py
azure/ai/translation/document/_patch.py
azure/ai/translation/document/_serialization.py
azure/ai/translation/document/_vendor.py
azure/ai/translation/document/_version.py
azure/ai/translation/document/py.typed
azure/ai/translation/document/_operations/__init__.py
azure/ai/translation/document/_operations/_operations.py
azure/ai/translation/document/_operations/_patch.py
azure/ai/translation/document/aio/__init__.py
azure/ai/translation/document/aio/_client.py
azure/ai/translation/document/aio/_configuration.py
azure/ai/translation/document/aio/_patch.py
azure/ai/translation/document/aio/_vendor.py
azure/ai/translation/document/aio/_operations/__init__.py
azure/ai/translation/document/aio/_operations/_operations.py
azure/ai/translation/document/aio/_operations/_patch.py
azure/ai/translation/document/models/__init__.py
azure/ai/translation/document/models/_enums.py
azure/ai/translation/document/models/_models.py
azure/ai/translation/document/models/_patch.py
azure_ai_translation_document-1.1.0.dist-info/LICENSE
azure_ai_translation_document-1.1.0.dist-info/METADATA
azure_ai_translation_document-1.1.0.dist-info/WHEEL
azure_ai_translation_document-1.1.0.dist-info/top_level.txt
azure_ai_translation_document-1.1.0.dist-info/RECORD
